exabyte_api_client/__init__.py
exabyte_api_client/_version.py
exabyte_api_client/endpoints/__init__.py
exabyte_api_client/endpoints/bank_entity.py
exabyte_api_client/endpoints/bank_materials.py
exabyte_api_client/endpoints/bank_workflows.py
exabyte_api_client/endpoints/charges.py
exabyte_api_client/endpoints/entity.py
exabyte_api_client/endpoints/enums.py
exabyte_api_client/endpoints/jobs.py
exabyte_api_client/endpoints/login.py
exabyte_api_client/endpoints/logout.py
exabyte_api_client/endpoints/materials.py
exabyte_api_client/endpoints/metaproperties.py
exabyte_api_client/endpoints/projects.py
exabyte_api_client/endpoints/properties.py
exabyte_api_client/endpoints/workflows.py
exabyte_api_client/endpoints/mixins/__init__.py
exabyte_api_client/endpoints/mixins/default.py
exabyte_api_client/endpoints/mixins/set.py
exabyte_api_client/utils/__init__.py
exabyte_api_client/utils/http.py
exabyte_api_client/utils/materials.py
exabyte_api_client-2025.9.13.post0.dist-info/licenses/LICENSE.md
exabyte_api_client-2025.9.13.post0.dist-info/METADATA
exabyte_api_client-2025.9.13.post0.dist-info/WHEEL
exabyte_api_client-2025.9.13.post0.dist-info/top_level.txt
exabyte_api_client-2025.9.13.post0.dist-info/RECORD
