Metadata-Version: 2.4
Name: exabyte-api-client
Version: 2025.9.13.post0
Summary: Exabyte Python Client for RESTful API
Home-page: https://github.com/Exabyte-io/api-client
Author: Exabyte Inc.
Author-email: info@mat3ra.com
Classifier: Programming Language :: Python
Classifier: Programming Language :: Python :: 3
Classifier: Development Status :: 3 - Alpha
Classifier: Intended Audience :: Developers
Classifier: Topic :: Software Development
Classifier: License :: OSI Approved :: Apache Software License
Requires-Python: >=3.6
License-File: LICENSE.md
Requires-Dist: requests>=2.26.0
Provides-Extra: test
Requires-Dist: coverage[toml]>=5.3; extra == "test"
Requires-Dist: mock>=1.3.0; extra == "test"
Dynamic: license-file
